python_mcp_server/__init__.py
python_mcp_server/server.py
python_mcp_server-1.0.1.dist-info/METADATA
python_mcp_server-1.0.1.dist-info/WHEEL
python_mcp_server-1.0.1.dist-info/entry_points.txt
python_mcp_server-1.0.1.dist-info/RECORD
