Metadata-Version: 2.4
Name: python-mcp-server
Version: 1.0.1
Summary: A world-class Python interpreter MCP server with session management, health monitoring, and FastMCP middleware
Project-URL: Homepage, https://deadmeme5441.github.io/python-mcp-server/
Project-URL: Repository, https://github.com/deadmeme5441/python-mcp-server
Project-URL: Issues, https://github.com/deadmeme5441/python-mcp-server/issues
Project-URL: Documentation, https://deadmeme5441.github.io/python-mcp-server/
Project-URL: Changelog, https://github.com/deadmeme5441/python-mcp-server/blob/main/CHANGELOG.md
Author-email: DeadMeme5441 <deadunderscorememe@gmail.com>
Keywords: fastmcp,health-monitoring,jupyter,mcp,mcp-server,python-interpreter,session-management
Classifier: Development Status :: 4 - Beta
Classifier: Framework :: AsyncIO
Classifier: Framework :: FastAPI
Classifier: Intended Audience :: Developers
Classifier: Intended Audience :: Science/Research
Classifier: License :: OSI Approved :: MIT License
Classifier: Programming Language :: Python :: 3
Classifier: Programming Language :: Python :: 3 :: Only
Classifier: Programming Language :: Python :: 3.10
Classifier: Programming Language :: Python :: 3.11
Classifier: Programming Language :: Python :: 3.12
Classifier: Topic :: Internet :: WWW/HTTP :: HTTP Servers
Classifier: Topic :: Scientific/Engineering
Classifier: Topic :: Software Development :: Libraries
Requires-Python: >=3.10
Requires-Dist: fastmcp>=1.0.0
Requires-Dist: ipykernel>=6.25.0
Requires-Dist: jupyter-client>=8.0.0
Requires-Dist: matplotlib>=3.7.0
Requires-Dist: pandas>=2.0.0
Requires-Dist: pathlib>=1.0.1
Requires-Dist: psutil>=5.9.0
Requires-Dist: uvicorn>=0.30.0
Provides-Extra: dev
Requires-Dist: httpx>=0.24.0; extra == 'dev'
Requires-Dist: mypy>=1.0.0; extra == 'dev'
Requires-Dist: pytest-asyncio>=0.21.0; extra == 'dev'
Requires-Dist: pytest>=7.0.0; extra == 'dev'
Requires-Dist: ruff>=0.1.0; extra == 'dev'
Provides-Extra: docs
Requires-Dist: mkdocs; extra == 'docs'
Requires-Dist: mkdocs-llmstxt; extra == 'docs'
Requires-Dist: mkdocs-material; extra == 'docs'
